tolino_notes/__init__.py
tolino_notes/__main__.py
tolino_notes/notes_writer.py
tolino_notes/tolino_note.py
tolino_notes-0.3.2.dist-info/LICENSE.txt
tolino_notes-0.3.2.dist-info/METADATA
tolino_notes-0.3.2.dist-info/WHEEL
tolino_notes-0.3.2.dist-info/entry_points.txt
tolino_notes-0.3.2.dist-info/RECORD
